searcheonet/__init__.py
searcheonet/searcheonet.py
searcheonet-0.1.0.dist-info/LICENSE
searcheonet-0.1.0.dist-info/WHEEL
searcheonet-0.1.0.dist-info/METADATA
searcheonet-0.1.0.dist-info/RECORD
