Metadata-Version: 2.1
Name: searcheonet
Version: 0.1.0
Summary: Python package that allows users to search for information about natural events from the NASA EONET API
License: Apache-2.0
Author: Alan Shen
Requires-Python: >=3.9,<4.0
Classifier: License :: OSI Approved :: Apache Software License
Classifier: Programming Language :: Python :: 3
Classifier: Programming Language :: Python :: 3.9
